fluss/__init__.py
fluss/api/schema.py
fluss/errors.py
fluss/fluss.py
fluss/funcs.py
fluss/rath.py
fluss/scalars.py
fluss/structures.py
fluss/traits.py
fluss/utils.py
fluss-0.1.61.dist-info/METADATA
fluss-0.1.61.dist-info/WHEEL
fluss-0.1.61.dist-info/RECORD
